setup.py
micropython_urllib.parse.egg-info/PKG-INFO
micropython_urllib.parse.egg-info/SOURCES.txt
micropython_urllib.parse.egg-info/dependency_links.txt
micropython_urllib.parse.egg-info/requires.txt
micropython_urllib.parse.egg-info/top_level.txt
urllib/parse.py